pyequib/__init__.py
pyequib/pyequib.py
pyequib/version.py
pyequib-0.4.3.data/data/LICENSE
pyequib-0.4.3.data/data/cel_diagnostic.dat
pyequib-0.4.3.data/data/cel_diagnostic2.dat
pyequib-0.4.3.data/data/cel_list.dat
pyequib-0.4.3.data/data/cel_list_doc.dat
pyequib-0.4.3.data/data/ext_list.dat
pyequib-0.4.3.data/data/hei_diagnostic.dat
pyequib-0.4.3.data/data/orl_diagnostic.dat
pyequib-0.4.3.data/data/orl_list.dat
pyequib-0.4.3.dist-info/AUTHORS.rst
pyequib-0.4.3.dist-info/LICENSE
pyequib-0.4.3.dist-info/METADATA
pyequib-0.4.3.dist-info/WHEEL
pyequib-0.4.3.dist-info/top_level.txt
pyequib-0.4.3.dist-info/RECORD
