Metadata-Version: 2.1
Name: pyequib
Version: 0.4.3
Summary: pyequib: Python Package for Plasma Diagnostics and Abundance Analysis
Home-page: https://equib.github.io/pyEQUIB/
Download-URL: https://github.com/equib/pyEQUIB
Author: Ashkbiz Danehkar
Author-email: ashkbiz.danehkar@students.mq.edu.au
License: http://www.gnu.org/licenses/gpl.html
Keywords: pyEQUIB,EQUIB,equilibrium,emissivities,plasma diagnostics,abundance analysis,astronomy,physics,astrophysics
Platform: any
License-File: LICENSE
License-File: AUTHORS.rst
Requires-Dist: numpy
Requires-Dist: scipy
Requires-Dist: atomneb
